setup.py
nucleo/__init__.py
nucleo/admin.py
nucleo/models.py
nucleo/permissions.py
nucleo/serializers.py
nucleo/tests.py
nucleo/views.py
nucleo.egg-info/PKG-INFO
nucleo.egg-info/SOURCES.txt
nucleo.egg-info/dependency_links.txt
nucleo.egg-info/not-zip-safe
nucleo.egg-info/requires.txt
nucleo.egg-info/top_level.txt